dbt/__init__.py
dbt/adapters/bigquery/__init__.py
dbt/adapters/bigquery/__version__.py
dbt/adapters/bigquery/clients.py
dbt/adapters/bigquery/column.py
dbt/adapters/bigquery/connections.py
dbt/adapters/bigquery/constants.py
dbt/adapters/bigquery/credentials.py
dbt/adapters/bigquery/dataset.py
dbt/adapters/bigquery/impl.py
dbt/adapters/bigquery/parse_model.py
dbt/adapters/bigquery/python_submissions.py
dbt/adapters/bigquery/relation.py
dbt/adapters/bigquery/retry.py
dbt/adapters/bigquery/token_suppliers.py
dbt/adapters/bigquery/utility.py
dbt/adapters/bigquery/catalogs/__init__.py
dbt/adapters/bigquery/catalogs/_biglake_metastore.py
dbt/adapters/bigquery/catalogs/_info_schema.py
dbt/adapters/bigquery/catalogs/_relation.py
dbt/adapters/bigquery/relation_configs/__init__.py
dbt/adapters/bigquery/relation_configs/_base.py
dbt/adapters/bigquery/relation_configs/_cluster.py
dbt/adapters/bigquery/relation_configs/_materialized_view.py
dbt/adapters/bigquery/relation_configs/_options.py
dbt/adapters/bigquery/relation_configs/_partition.py
dbt/adapters/bigquery/relation_configs/_policies.py
dbt/include/bigquery/__init__.py
dbt/include/bigquery/dbt_project.yml
dbt/include/bigquery/profile_template.yml
dbt/include/bigquery/macros/adapters.sql
dbt/include/bigquery/macros/etc.sql
dbt/include/bigquery/macros/adapters/apply_grants.sql
dbt/include/bigquery/macros/adapters/columns.sql
dbt/include/bigquery/macros/catalog/by_relation.sql
dbt/include/bigquery/macros/catalog/by_schema.sql
dbt/include/bigquery/macros/catalog/catalog.sql
dbt/include/bigquery/macros/materializations/clone.sql
dbt/include/bigquery/macros/materializations/copy.sql
dbt/include/bigquery/macros/materializations/incremental.sql
dbt/include/bigquery/macros/materializations/materialized_view.sql
dbt/include/bigquery/macros/materializations/seed.sql
dbt/include/bigquery/macros/materializations/snapshot.sql
dbt/include/bigquery/macros/materializations/table.sql
dbt/include/bigquery/macros/materializations/view.sql
dbt_bigquery-1.10.0.dist-info/METADATA
dbt_bigquery-1.10.0.dist-info/WHEEL
dbt_bigquery-1.10.0.dist-info/licenses/LICENSE
dbt_bigquery-1.10.0.dist-info/RECORD
