Metadata-Version: 2.4
Name: dbt-bigquery
Version: 1.10.0
Summary: The BigQuery adapter plugin for dbt
Project-URL: Homepage, https://github.com/dbt-labs/dbt-adapters/tree/main/dbt-bigquery
Project-URL: Documentation, https://docs.getdbt.com
Project-URL: Repository, https://github.com/dbt-labs/dbt-adapters.git#subdirectory=dbt-bigquery
Project-URL: Issues, https://github.com/dbt-labs/dbt-adapters/issues
Project-URL: Changelog, https://github.com/dbt-labs/dbt-adapters/blob/main/dbt-bigquery/CHANGELOG.md
Author-email: dbt Labs <info@dbtlabs.com>
Maintainer-email: dbt Labs <info@dbtlabs.com>
License-File: LICENSE
Keywords: adapter,adapters,bigquery,database,dbt,dbt Cloud,dbt Core,dbt Labs,dbt-core,elt,google
Classifier: Development Status :: 5 - Production/Stable
Classifier: License :: OSI Approved :: Apache Software License
Classifier: Operating System :: MacOS :: MacOS X
Classifier: Operating System :: Microsoft :: Windows
Classifier: Operating System :: POSIX :: Linux
Classifier: Programming Language :: Python :: 3.9
Classifier: Programming Language :: Python :: 3.10
Classifier: Programming Language :: Python :: 3.11
Classifier: Programming Language :: Python :: 3.12
Requires-Python: >=3.9.0
Requires-Dist: dbt-adapters<2.0,>=1.16
Requires-Dist: dbt-common<2.0,>=1.10
Requires-Dist: dbt-core>=1.10.0rc0
Requires-Dist: google-api-core>=2.11.0
Requires-Dist: google-auth>=2.29.0
Requires-Dist: google-cloud-aiplatform>=1.72.0
Requires-Dist: google-cloud-bigquery[pandas]<4.0,>=3.0
Requires-Dist: google-cloud-dataproc~=5.0
Requires-Dist: google-cloud-storage<3.2,>=2.4
Requires-Dist: nbformat>=5.10.4
